{
  "map_info": [
    {
      "DWG": {
        "marker_info_list": []
      },
      "BIM Data": {
        "marker_info_list": [
          {
            "marker_position": {
              "leftPercentage": 50,
              "topPercentage": 50
            },
            "marker_size": {
              "height": 32,
              "width": 32
            },
            "marker_metadata": {
              "data": ""
            },
            "markerType": "info"
          },
          {
            "marker_position": {
              "leftPercentage": 27,
              "topPercentage": 40
            },
            "marker_size": {
              "height": 32,
              "width": 32
            },
            "marker_metadata": {
              "data": ""
            },
            "markerType": "info"
          }
        ]
      },
      "360°": {
        "marker_info_list": [
          {
            "marker_position": {
              "leftPercentage": 70,
              "topPercentage": 60
            },
            "marker_size": {
              "height": 32,
              "width": 32
            },
            "marker_metadata": {
              "data": "",
              "redirect_uri": "http://pano-dev.autodesk.com/pano.html?url=jpgs/41391972-49d3-4b52-87fb-cf152de5c032"
            },
            "markerType": "hyperlink"
          },
          {
            "marker_position": {
              "leftPercentage": 87,
              "topPercentage": 50
            },
            "marker_size": {
              "height": 32,
              "width": 32
            },
            "marker_metadata": {
              "data": "",
              "redirect_uri": "http://pano-dev.autodesk.com/pano.html?url=jpgs/41391972-49d3-4b52-87fb-cf152de5c032"
            },
            "markerType": "hyperlink"
          },
          {
            "marker_position": {
              "leftPercentage": 60,
              "topPercentage": 70
            },
            "marker_size": {
              "height": 32,
              "width": 32
            },
            "marker_metadata": {
              "data": "",
              "redirect_uri": "http://pano-dev.autodesk.com/pano.html?url=jpgs/41391972-49d3-4b52-87fb-cf152de5c032"
            },
            "markerType": "hyperlink"
          },
          {
            "marker_position": {
              "leftPercentage": 37,
              "topPercentage": 90
            },
            "marker_size": {
              "height": 32,
              "width": 32
            },
            "marker_metadata": {
              "data": "",
              "redirect_uri": "http://pano-dev.autodesk.com/pano.html?url=jpgs/41391972-49d3-4b52-87fb-cf152de5c032"
            },
            "markerType": "hyperlink"
          }
        ]
      },
      "AR": {
        "marker_info_list": [
          {
            "marker_position": {
              "leftPercentage": 50,
              "topPercentage": 60
            },
            "marker_size": {
              "height": 32,
              "width": 32
            },
            "marker_metadata": {
              "data": ""
            },
            "markerType": "info"
          },
          {
            "marker_position": {
              "leftPercentage": 37,
              "topPercentage": 50
            },
            "marker_size": {
              "height": 32,
              "width": 32
            },
            "marker_metadata": {
              "data": ""
            },
            "markerType": "info"
          },
          {
            "marker_position": {
              "leftPercentage": 50,
              "topPercentage": 50
            },
            "marker_size": {
              "height": 32,
              "width": 32
            },
            "marker_metadata": {
              "data": ""
            },
            "markerType": "info"
          },
          {
            "marker_position": {
              "leftPercentage": 17,
              "topPercentage": 50
            },
            "marker_size": {
              "height": 32,
              "width": 32
            },
            "marker_metadata": {
              "data": ""
            },
            "markerType": "info"
          }
        ]
      }
    }
  ],
  "url": "https://s4.nofilecdn.io/g/Q4M6Nvg3fePGrXY8bz5QXx52B91OCovTK1z2w1ctG1Cm49UMtswnDyP24Z6g0JPX/map.pdf"
}